pyshadowserver/__init__.py
pyshadowserver/api.py
pyshadowserver-0.1.dist-info/LICENSE
pyshadowserver-0.1.dist-info/METADATA
pyshadowserver-0.1.dist-info/WHEEL
pyshadowserver-0.1.dist-info/top_level.txt
pyshadowserver-0.1.dist-info/RECORD
