Metadata-Version: 2.1
Name: pyshadowserver
Version: 0.1
Summary: Python 3 library for Shadow Server reports
Home-page: https://github.com/te-k/pyshadowserver
Author: Etienne Maynier
Author-email: tek@randhome.io
License: MIT
Keywords: security,mobile,forensics,malware
Classifier: Intended Audience :: Information Technology
Classifier: Operating System :: OS Independent
Classifier: Programming Language :: Python
Classifier: License :: OSI Approved :: MIT License
Requires-Python: >=3.8
License-File: LICENSE
Requires-Dist: requests
Requires-Dist: appdirs
